regx_entities/__init__.py
regx_entities/ents.py
dave_misc-0.1.0.dist-info/METADATA
dave_misc-0.1.0.dist-info/WHEEL
dave_misc-0.1.0.dist-info/top_level.txt
dave_misc-0.1.0.dist-info/RECORD
