Metadata-Version: 2.1
Name: dave-misc
Version: 0.1.0
Summary: Dave micro services
Home-page: https://www.iamdave.ai/
Author: Dinesh
Author-email: dinesh@iamdave.ai
License: MIT
Platform: UNKNOWN
Classifier: Intended Audience :: Developers
Classifier: License :: OSI Approved :: MIT License
Classifier: Programming Language :: Python
Classifier: Programming Language :: Python :: 3
Classifier: Programming Language :: Python :: 3.6
Classifier: Programming Language :: Python :: 3.7
Classifier: Programming Language :: Python :: 3.8
Classifier: Programming Language :: Python :: 3.9
Classifier: Operating System :: OS Independent
Requires-Dist: python-dateutil
Requires-Dist: pytz
Requires-Dist: six
